setup.py
stat.py
micropython_stat.egg-info/PKG-INFO
micropython_stat.egg-info/SOURCES.txt
micropython_stat.egg-info/dependency_links.txt
micropython_stat.egg-info/top_level.txt