Metadata-Version: 1.0
Name: micropython-stat
Version: 0.5
Summary: CPython stat module ported to MicroPython
Home-page: https://github.com/micropython/micropython/issues/405
Author: MicroPython Developers
Author-email: micro-python@googlegroups.com
License: Python
Platform: UNKNOWN
